{"jdata":[{"k_ele":[{"e":"僧","p":true}],"r_ele":[{"r":"そう","p":true}],"sense":[{"gloss":"monk, priest","pos":["n"]},{"gloss":"sangha (the Buddhist community)","pos":["n"],"m":["abbr"],"x":["僧伽・そうぎゃ"]}]},{"k_ele":[{"e":"僧侶","p":true}],"r_ele":[{"r":"そうりょ","p":true}],"sense":[{"gloss":"priest, monk, bonze","pos":["n"],"f":["Buddh"]}]},{"k_ele":[{"e":"小僧","p":true}],"r_ele":[{"r":"こぞう","p":true}],"sense":[{"gloss":"youngster, boy, kid, brat","pos":["n"]},{"gloss":"young Buddhist monk, young bonze","pos":["n"]},{"gloss":"young shop-boy, errand boy, apprentice","pos":["n"]}]},{"k_ele":[{"e":"尼僧","p":true}],"r_ele":[{"r":"にそう","p":true}],"sense":[{"gloss":"Buddhist nun","pos":["n"]},{"gloss":"Catholic nun, sister","pos":["n"]}]},{"k_ele":[{"e":"僧院","p":true}],"r_ele":[{"r":"そういん","p":true}],"sense":[{"gloss":"monastery, temple","pos":["n"]}]},{"k_ele":[{"e":"高僧","p":true}],"r_ele":[{"r":"こうそう","p":true}],"sense":[{"gloss":"high priest, highly-ranked priest","pos":["n"]},{"gloss":"virtuous priest, priest of great sanctity and learning","pos":["n"]}]},{"k_ele":[{"e":"禅僧","p":true}],"r_ele":[{"r":"ぜんそう","p":true}],"sense":[{"gloss":"Zen priest","pos":["n"]}]},{"k_ele":[{"e":"僧籍","p":true}],"r_ele":[{"r":"そうせき","p":true}],"sense":[{"gloss":"priesthood","pos":["n"],"f":["Buddh"]}]},{"k_ele":[{"e":"若造","p":true},{"e":"若蔵"},{"e":"若僧"}],"r_ele":[{"r":"わかぞう","p":true}],"sense":[{"gloss":"youngster, neophyte, greenhorn","pos":["n"]}],"m":["derog"]},{"k_ele":[{"e":"いたずら小僧"},{"e":"イタズラ小僧"},{"e":"悪戯小僧"}],"r_ele":[{"r":"いたずらこぞう"}],"sense":[{"gloss":"mischievous boy","pos":["n"]}]},{"k_ele":[{"e":"悪僧"}],"r_ele":[{"r":"あくそう"}],"sense":[{"gloss":"dissolute priest, depraved monk","pos":["n"]},{"gloss":"ferocious warrior monk","pos":["n"]}]},{"k_ele":[{"e":"下僧"}],"r_ele":[{"r":"げそう"}],"sense":[{"gloss":"low-rank priest","pos":["n"]}]},{"k_ele":[{"e":"学僧"}],"r_ele":[{"r":"がくそう"}],"sense":[{"gloss":"learned priest pursuing his studies","pos":["n"]}]},{"k_ele":[{"e":"虚無僧"}],"r_ele":[{"r":"こむそう"}],"sense":[{"gloss":"begging Zen priest of the Fuke sect (wearing a sedge hood and playing a shakuhachi flute)","pos":["n"]}]},{"k_ele":[{"e":"軍僧"}],"r_ele":[{"r":"ぐんそう"}],"sense":[{"gloss":"chaplain","pos":["n"]}]},{"k_ele":[{"e":"師僧"}],"r_ele":[{"r":"しそう"}],"sense":[{"gloss":"priestly teacher","pos":["n"]}]},{"k_ele":[{"e":"侍僧"}],"r_ele":[{"r":"じそう"}],"sense":[{"gloss":"acolyte","pos":["n"]}]},{"k_ele":[{"e":"住僧"}],"r_ele":[{"r":"じゅうそう"}],"sense":[{"gloss":"chief priest (of a Buddhist temple)","pos":["n"]}]},{"k_ele":[{"e":"小便小僧"}],"r_ele":[{"r":"しょうべんこぞう"}],"sense":[{"gloss":"Manneken Pis (cupid-like statue urinating into a fountain), Petit Julien","pos":["n"]}]},{"k_ele":[{"e":"僧庵"}],"r_ele":[{"r":"そうあん"}],"sense":[{"gloss":"priest's hermitage","pos":["n"]}]},{"k_ele":[{"e":"僧庵生活"}],"r_ele":[{"r":"そうあんせいかつ"}],"sense":[{"gloss":"hermit life","pos":["n"]}]},{"k_ele":[{"e":"僧位"}],"r_ele":[{"r":"そうい"}],"sense":[{"gloss":"rank (of a monk)","pos":["n"],"f":["Buddh"]}]},{"k_ele":[{"e":"僧衣"}],"r_ele":[{"r":"そうい"}],"sense":[{"gloss":"priest's garb","pos":["n"]}]},{"k_ele":[{"e":"僧家"}],"r_ele":[{"r":"そうか"},{"r":"そうけ"}],"sense":[{"gloss":"Buddhist temple","pos":["n"]},{"gloss":"Buddhist priest","pos":["n"]}],"m":["rare"]},{"k_ele":[{"e":"僧形"}],"r_ele":[{"r":"そうぎょう"}],"sense":[{"gloss":"the form of a Buddhist priest, priestly attire","pos":["n"]}]},{"k_ele":[{"e":"僧号"}],"r_ele":[{"r":"そうごう"}],"sense":[{"gloss":"priest's religious name","pos":["n"]}]},{"k_ele":[{"e":"僧寺"}],"r_ele":[{"r":"そうじ"}],"sense":[{"gloss":"Buddhist priest, temple with a resident priest","pos":["n"]}]},{"k_ele":[{"e":"僧職"}],"r_ele":[{"r":"そうしょく"}],"sense":[{"gloss":"priesthood","pos":["n","adj-no"],"f":["Buddh"]}]},{"k_ele":[{"e":"僧正"}],"r_ele":[{"r":"そうじょう"}],"sense":[{"gloss":"high Buddhist priest","pos":["n"]}]},{"k_ele":[{"e":"僧俗"}],"r_ele":[{"r":"そうぞく"}],"sense":[{"gloss":"priests and laymen","pos":["n"]}]}],"sdata":[{"j":"また↑僕↑↓ぼく↓をかつごうとしているのかい、このいたずら↑小僧↑↓こぞう↓め。","e":"Are you going to play tricks on me again, you naughty boy?"},{"j":"その↑僧↑↓そう↓は↑子供↑↓こども↓↑達↑↓たち↓の↑遊↑↓あそ↓びに↑仲間入↑↓なかまい↓りした。","e":"The priest participated in the children's games."},{"j":"その↑僧↑↓そう↓は↑子供↑↓こども↓たちの↑遊↑↓あそ↓びに↑参加↑↓さんか↓した。","e":"The priest participated in the children's game."},{"j":"そのいたずら↑小僧↑↓こぞう↓から↑目↑↓め↓を↑離↑↓はな↓すな。","e":"Keep an eye on the naughty kid."},{"j":"あのわんぱく↑小僧↑↓こぞう↓のいたずらには↑閉口↑↓へいこう↓する。","e":"That naughty boy annoys me by his pranks."},{"j":"↑村人↑↓むらびと↓はみなかわるがわる↑僧↑↓そう↓にあいさつした。","e":"All the villagers in turn saluted the priest."},{"j":"↑当時↑↓とうじ↓は↑修道↑↓しゅうどう↓↑僧↑↓そう↓↑達↑↓たち↓が↑修道院↑↓しゅうどういん↓でよくテニスをしていた。","e":"Monks used to play tennis in monasteries."},{"j":"↑尼僧↑↓にそう↓はお↑祈↑↓いの↓りをして↑十字↑↓じゅうじ↓を↑切↑↓き↓った。","e":"The nun prayed and crossed herself."},{"j":"↑彼↑↓かれ↓はよく↑近所↑↓きんじょ↓の↑腕白↑↓わんぱく↓↑小僧↑↓こぞう↓たちをののしったものだ。","e":"He would swear at the naughty boys in the neighborhood."},{"j":"↑彼↑↓かれ↓は↑僧侶↑↓そうりょ↓に↑近↑↓ちか↓い↑禁欲↑↓きんよく↓↑生活↑↓せいかつ↓をしている。","e":"He practices austerities almost like a monk."},{"j":"↑彼女↑↓かのじょ↓は↑腕白↑↓わんぱく↓↑小僧↑↓こぞう↓に↑腹↑↓はら↓を↑立↑↓た↓てている。","e":"She got angry with the naughty boy."},{"j":"↑門前↑↓もんぜん↓の↑小僧↑↓こぞう↓↑習↑↓なら↓わぬ↑経↑↓きょう↓を↑読↑↓よ↓む。","e":"A saint's maid quotes Latin."},{"j":"↑禅僧↑↓ぜんそう↓は↑新宿↑↓しんじゅく↓↑駅↑↓えき↓のあたりで↑托鉢↑↓たくはつ↓しています。","e":"Zen priests beg for alms near Shinjuku station."},{"j":"↑四↑↓よん↓↑十↑↓じゅう↓↑五↑↓ご↓↑十↑↓じゅう↓は↑鼻↑↓はな↓たれ↑小僧↑↓こぞう↓。","e":"A 40- or 50-year-old is a snot-nosed brat."},{"j":"トムはわんぱく↑小僧↑↓こぞう↓なんだ。","e":"Tom is a naughty boy."},{"j":"↑小便↑↓しょうべん↓↑小僧↑↓こぞう↓の↑本家↑↓ほんけ↓↑本元↑↓ほんもと↓は、ベルギー・ブリュッセルにあるジュリアン↑君↑↓くん↓です。","e":"The original for Manneken Pis was a boy named Julian from Brussels, Belgium."},{"j":"↑子↑↓こ↓どもの↑頃↑↓ころ↓「↑四↑↓よ↓つ↑目↑↓め↓↑小僧↑↓こぞう↓」とからかわれたことがあります。","e":"As a child, I was teased by being called \"four-eyes\"."}],"kdata":{"on":["ソウ"],"jlpt":1,"meanings":["monk","Buddhist priest"],"freq":1724,"comp":[["曾","亻"]],"t":1689},"c":{"meanings":["monk","Buddhist priest"],"on":["ソウ"]}}