{"jdata":[{"k_ele":[{"e":"硬い","p":true},{"e":"固い","p":true},{"e":"堅い","p":true},{"e":"緊い","i":["iK"]}],"r_ele":[{"r":"かたい","p":true}],"sense":[{"gloss":"hard, solid, tough","pos":["adj-i"]},{"gloss":"stiff, tight, wooden, unpolished (e.g. writing)","pos":["adj-i"]},{"gloss":"strong, firm (not viscous or easily moved)","pos":["adj-i"]},{"gloss":"safe, steady, honest, steadfast","pos":["adj-i"]},{"gloss":"obstinate, stubborn","pos":["adj-i"]},{"gloss":"bookish, formal, stuffy","pos":["adj-i"],"ant":["砕けた"]}]},{"k_ele":[{"e":"中堅","p":true}],"r_ele":[{"r":"ちゅうけん","p":true}],"sense":[{"gloss":"nucleus, backbone, mainstay, key figure","pos":["n"]},{"gloss":"medium-level, mid-level, middle-ranking, midsize","pos":["adj-no","n"]},{"gloss":"main body (of troops), crack troops, select troops","pos":["n"]},{"gloss":"center field, centre field, center fielder, centre fielder","pos":["n"],"f":["baseb"]},{"gloss":"athlete competing in the middle-number match in a team competition, i.e. second in 3-on-3, third in 5-on-5 (kendo, judo, etc.)","pos":["n"],"x":["先鋒・せんぽう・2"]}]},{"k_ele":[{"e":"堅持","p":true}],"r_ele":[{"r":"けんじ","p":true}],"sense":[{"gloss":"holding on to, sticking to","pos":["n","vs","vt"]}]},{"k_ele":[{"e":"堅実","p":true},{"e":"健実"}],"r_ele":[{"r":"けんじつ","p":true}],"sense":[{"gloss":"steady, sound, stable, safe (e.g. business), reliable, trustworthy, solid","pos":["adj-na"]}]},{"k_ele":[{"e":"堅調","p":true}],"r_ele":[{"r":"けんちょう","p":true}],"sense":[{"gloss":"firm (market), bullish","pos":["adj-na","n"],"ant":["軟調・なんちょう・1"]},{"gloss":"strong (sales, economy, etc.), steady, sound","pos":["adj-na","n"]}]},{"k_ele":[{"e":"堅固","p":true}],"r_ele":[{"r":"けんご","p":true}],"sense":[{"gloss":"solid, strong, firm","pos":["adj-na","n"]}]},{"k_ele":[{"e":"堅苦しい","p":true},{"e":"固苦しい","p":true,"i":["iK"]}],"r_ele":[{"r":"かたくるしい","p":true},{"r":"かたぐるしい","i":["ik"]}],"sense":[{"gloss":"formal, strict, ceremonious, stiff","pos":["adj-i"]}]},{"k_ele":[{"e":"手堅い","p":true}],"r_ele":[{"r":"てがたい","p":true}],"sense":[{"gloss":"sound, sure, safe, secure, trustworthy, reliable, solid","pos":["adj-i"]},{"gloss":"steady, firm","pos":["adj-i"]}]},{"k_ele":[{"e":"硬さ","p":true},{"e":"固さ","p":true},{"e":"堅さ","p":true}],"r_ele":[{"r":"かたさ","p":true}],"sense":[{"gloss":"firmness, hardness, stiffness, honesty","pos":["n"]}]},{"k_ele":[{"e":"堅気","p":true}],"r_ele":[{"r":"かたぎ","p":true},{"r":"カタギ"}],"sense":[{"gloss":"honest, respectable, decent","pos":["adj-na","n"]},{"gloss":"respectable occupation (i.e. not yakuza, prostitute, etc.)","pos":["n","adj-no"]},{"gloss":"person in a respectable occupation","pos":["n"]}]},{"k_ele":[{"e":"堅守","p":true}],"r_ele":[{"r":"けんしゅ","p":true}],"sense":[{"gloss":"strong defense, strong defence","pos":["n","vs","vt"]}]},{"k_ele":[{"e":"底堅い","p":true}],"r_ele":[{"r":"そこがたい","p":true}],"sense":[{"gloss":"stable (market) after having bottomed out","pos":["adj-i"]}]},{"k_ele":[{"e":"固め"},{"e":"硬め"},{"e":"堅め"},{"e":"固目"},{"e":"硬目"},{"e":"堅目"}],"r_ele":[{"r":"かため"}],"sense":[{"gloss":"somewhat hard, somewhat firm, fairly hard, on the hard side","pos":["adj-no","adj-na","n"],"ant":["柔らかめ"]}]},{"k_ele":[{"e":"堅"}],"r_ele":[{"r":"けん"}],"sense":[{"gloss":"strength, solidity, firmness","pos":["n"]},{"gloss":"armour, armor","pos":["n"]}],"m":["rare"]},{"k_ele":[{"e":"固める","p":true},{"e":"堅める","i":["iK"]}],"r_ele":[{"r":"かためる","p":true}],"sense":[{"gloss":"to harden, to freeze, to strengthen, to solidify, to make (a fist), to tramp down (snow, dirt)","pos":["v1","vt"],"x":["土を固める・つちをかためる"]},{"gloss":"to put together, to collect, to gather, to consolidate","pos":["v1","vt"]},{"gloss":"to make secure, to stabilize, to settle down, to strengthen (belief, resolution, etc.), to establish (evidence)","pos":["v1","vt"],"x":["身を固める・みをかためる・1"]},{"gloss":"to fortify, to reinforce, to support","pos":["v1","vt"],"x":["国境を固める・こっきょうをかためる","嘘で固める・うそでかためる"]},{"gloss":"to wear for a specific purpose (armor, coat, etc.)","pos":["v1","vt"]},{"gloss":"to swear, to resolutely vow, to sincerely promise","pos":["v1","vt"]},{"gloss":"to tie tightly, to fasten","pos":["v1","vt"]},{"gloss":"to hold a bow fully drawn","pos":["v1","vt"]}]},{"k_ele":[{"e":"堅牢"}],"r_ele":[{"r":"けんろう"}],"sense":[{"gloss":"solid, strong, sturdy, durable, stout","pos":["adj-na","n"]}]},{"k_ele":[{"e":"鰹","p":true},{"e":"松魚"},{"e":"堅魚"}],"r_ele":[{"r":"かつお","p":true},{"r":"しょうぎょ"},{"r":"カツオ"}],"sense":[{"gloss":"skipjack tuna (Katsuwonus pelamis), oceanic bonito, victorfish","pos":["n"]}],"m":["uk"]},{"k_ele":[{"e":"久方"},{"e":"久堅"}],"r_ele":[{"r":"ひさかた"}],"sense":[{"gloss":"sky, moon","pos":["n"]}],"m":["arch"]},{"k_ele":[{"e":"堅果"}],"r_ele":[{"r":"けんか"}],"sense":[{"gloss":"nut","pos":["n","adj-no"]}]},{"k_ele":[{"e":"堅城"}],"r_ele":[{"r":"けんじょう"}],"sense":[{"gloss":"strong fortress","pos":["n"]}]},{"k_ele":[{"e":"堅陣"}],"r_ele":[{"r":"けんじん"}],"sense":[{"gloss":"stronghold","pos":["n"]}]},{"k_ele":[{"e":"堅忍"}],"r_ele":[{"r":"けんにん"}],"sense":[{"gloss":"perseverance","pos":["n","vs","vt","vi"]}]},{"k_ele":[{"e":"堅忍不抜"}],"r_ele":[{"r":"けんにんふばつ"}],"sense":[{"gloss":"indomitable perseverance, invincible fortitude","pos":["adj-na","n"]}],"m":["yoji"]},{"k_ele":[{"e":"堅物"}],"r_ele":[{"r":"かたぶつ"}],"sense":[{"gloss":"straight-laced person, stubborn person","pos":["n"]}]},{"k_ele":[{"e":"堅塁"},{"e":"堅累"}],"r_ele":[{"r":"けんるい"}],"sense":[{"gloss":"stronghold","pos":["n"]}]},{"k_ele":[{"e":"中堅手"}],"r_ele":[{"r":"ちゅうけんしゅ"}],"sense":[{"gloss":"center fielder, centre fielder","pos":["n"],"f":["baseb"]}]},{"k_ele":[{"e":"堅人"}],"r_ele":[{"r":"かたじん"}],"sense":[{"gloss":"square, trustworthy person","pos":["n"]}]},{"k_ele":[{"e":"口堅い"},{"e":"口固い"}],"r_ele":[{"r":"くちがたい"}],"sense":[{"gloss":"discreet, tight-lipped","pos":["adj-i"]}]},{"k_ele":[{"e":"昔気質"},{"e":"昔かたぎ"},{"e":"昔堅気"}],"r_ele":[{"r":"むかしかたぎ"}],"sense":[{"gloss":"old-fashioned way of thinking, old-fashioned spirit","pos":["n"]},{"gloss":"old-fashioned","pos":["adj-no","adj-na"]}]},{"k_ele":[{"e":"物堅い"}],"r_ele":[{"r":"ものがたい"}],"sense":[{"gloss":"honest, upright, faithful, reliable","pos":["adj-i"]}]},{"k_ele":[{"e":"堅太り"},{"e":"固太り"}],"r_ele":[{"r":"かたぶとり"}],"sense":[{"gloss":"solidly built person","pos":["adj-na","n"]}]},{"k_ele":[{"e":"堅木"}],"r_ele":[{"r":"かたぎ"}],"sense":[{"gloss":"hardwood","pos":["n"]}]},{"k_ele":[{"e":"堅信礼"}],"r_ele":[{"r":"けんしんれい"}],"sense":[{"gloss":"(the Christian sacrament of) confirmation","pos":["n"]}]},{"k_ele":[{"e":"堅炭"}],"r_ele":[{"r":"かたずみ"}],"sense":[{"gloss":"hard charcoal","pos":["n"]}]},{"k_ele":[{"e":"鰹木"},{"e":"堅魚木"}],"r_ele":[{"r":"かつおぎ"}],"sense":[{"gloss":"log on the roof of a shrine set perpendicular to the ridgepole","pos":["n"]}]},{"k_ele":[{"e":"義理堅い"}],"r_ele":[{"r":"ぎりがたい"}],"sense":[{"gloss":"possessed of a strong sense of duty","pos":["adj-i"]}]},{"k_ele":[{"e":"身持ちの堅い女"}],"r_ele":[{"r":"みもちのかたいおんな"}],"sense":[{"gloss":"chaste woman, virtuous woman","pos":["exp","n"]}]},{"k_ele":[{"e":"堅い商売"}],"r_ele":[{"r":"かたいしょうばい"}],"sense":[{"gloss":"sound business","pos":["exp","n"]}]},{"k_ele":[{"e":"堅パン"}],"r_ele":[{"r":"かたパン"}],"sense":[{"gloss":"hard biscuits, hardtack","pos":["n"]}]},{"k_ele":[{"e":"堅材"}],"r_ele":[{"r":"けんざい"}],"sense":[{"gloss":"hard wood","pos":["n"]}]},{"k_ele":[{"e":"堅志"}],"r_ele":[{"r":"けんし"}],"sense":[{"gloss":"iron purpose","pos":["n"]}]},{"k_ele":[{"e":"志操堅固"}],"r_ele":[{"r":"しそうけんご"}],"sense":[{"gloss":"being faithful to one's principles, being of firm purpose and deep commitment, constancy, true blue","pos":["n","adj-na"]}],"m":["yoji"]},{"k_ele":[{"e":"要害堅固"}],"r_ele":[{"r":"ようがいけんご"}],"sense":[{"gloss":"(a fortress being) impregnable, unassailable","pos":["n","adj-no"]}],"m":["yoji"]},{"k_ele":[{"e":"意志堅固"}],"r_ele":[{"r":"いしけんご"}],"sense":[{"gloss":"strong determination, strong-willed, having strong will power, firmness of purpose","pos":["n","adj-na"]}],"m":["yoji"]},{"k_ele":[{"e":"堅忍持久"}],"r_ele":[{"r":"けんにんじきゅう"}],"sense":[{"gloss":"dogged perseverance, untiring patience","pos":["n"]}]},{"k_ele":[{"e":"堅白同異"}],"r_ele":[{"r":"けんぱくどうい"}],"sense":[{"gloss":"sophism, sophistry, quibbling","pos":["n"]}],"m":["yoji"]},{"k_ele":[{"e":"堅牢堅固"}],"r_ele":[{"r":"けんろうけんご"}],"sense":[{"gloss":"firm and solid, stout and durable","pos":["n","adj-na"]}],"m":["yoji"]},{"k_ele":[{"e":"金剛堅固"}],"r_ele":[{"r":"こんごうけんご"}],"sense":[{"gloss":"firm and solid, sturdy and indestructible, unshakable, adamantine","pos":["n"]}]},{"k_ele":[{"e":"道心堅固"}],"r_ele":[{"r":"どうしんけんご"}],"sense":[{"gloss":"being of firm (unshakable) faith and strict practice","pos":["n","adj-na"]}],"m":["yoji"]},{"k_ele":[{"e":"道徳堅固"}],"r_ele":[{"r":"どうとくけんご"}],"sense":[{"gloss":"of strict morals (moral principles), highly moral","pos":["n","adj-na"]}]}],"sdata":[{"j":"↑堅↑↓かた↓い↑書↑↓か↓き↑物↑↓もの↓は↑大嫌↑↓だいきら↓いだ。","e":"I utterly despise formal writing!"},{"j":"↑家↑↓いえ↓は↑堅固↑↓けんご↓なセメントの↑基盤↑↓きばん↓の↑上↑↓じょう↓に↑建↑↓た↓てられる。","e":"A house is built on top of a solid foundation of cement."},{"j":"↑僕↑↓ぼく↓は↑彼↑↓かれ↓の↑無実↑↓むじつ↓を↑堅↑↓かた↓く↑信↑↓しん↓じている。","e":"I have a firm belief in his innocence."},{"j":"ボールを↑丸↑↓まる↓く、そして↑堅↑↓かた↓くするために↑麦↑↓むぎ↓わらをいっぱいに↑詰↑↓つ↓め↑込↑↓こ↓んでいました。","e":"They filled them with straw to make them round and hard."},{"j":"ファッション↑研究↑↓けんきゅう↓にニューヨークに↑行↑↓い↓くのだと↑彼女↑↓かのじょ↓は↑堅↑↓かた↓く↑心↑↓こころ↓にきめている。","e":"She's intent on going to New York to study fashion."},{"j":"ダイヤモンドは↑本来↑↓ほんらい↓↑堅↑↓かた↓いものだ。","e":"Diamond is essentially hard."},{"j":"それはまるで↑岩↑↓いわ↓のように↑堅↑↓かた↓かった。","e":"It was hard as rock."},{"j":"その↑走者↑↓そうしゃ↓は↑堅↑↓かた↓い↑筋肉↑↓きんにく↓をしている。","e":"The runner has firm muscles."},{"j":"その↑市↑↓し↓の↑防御↑↓ぼうぎょ↓は↑堅固↑↓けんご↓だ。","e":"The defenses of the city are strong."},{"j":"その↑機械↑↓きかい↓の↑骨組↑↓ほねぐ↓みは↑堅↑↓かた↓くなければならない。","e":"The frame of the machine should be rigid."},{"j":"この↑机↑↓つくえ↓は↑堅↑↓かた↓い↑材質↑↓ざいしつ↓の↑木↑↓き↓でできている。","e":"This desk is made of hard wood."},{"j":"このベッドは↑堅↑↓かた↓くて↑眠↑↓ねむ↓れない。","e":"This bed is too hard to sleep in."},{"j":"このステーキは↑堅↑↓かた↓すぎる。","e":"This steak is too tough."},{"j":"ここに↑鉛筆↑↓えんぴつ↓が↑二↑↓に↓↑本↑↓ほん↓ある。↑一↑↓いち↓↑本↑↓ほん↓は↑堅↑↓かた↓く、もう↑一↑↓いち↓↑本↑↓ほん↓は↑柔↑↓やわ↓らかい。","e":"Here are two pencils: one is hard, and the other soft."},{"j":"↑堅苦↑↓かたくる↓しいことはぬきにしましょう。","e":"Let's dispense with formalities."},{"j":"↑堅苦↑↓かたくる↓しい↑礼儀↑↓れいぎ↓は↑一↑↓いち↓↑切抜↑↓きりぬ↓きにしましょう。","e":"Let's do away with all formalities."},{"j":"↑堅苦↑↓かたくる↓しく↑考↑↓かんが↓えないで、くつろいでください。","e":"Don't stand on ceremony. Just make yourself at home."},{"j":"↑堅実↑↓けんじつ↓な↑草↑↓くさ↓の↑根↑↓ね↓レベルの↑運動↑↓うんどう↓を↑築↑↓きず↓きあげることに↑集中↑↓しゅうちゅう↓しなければならない。","e":"We must focus on building a solid grass-roots movement."},{"j":"↑建築↑↓けんちく↓↑物↑↓ぶつ↓は、↑現在↑↓げんざい↓では↑昔↑↓むかし↓よりずっと↑堅牢↑↓けんろう↓になっている。","e":"Buildings are much stronger now than they used to be."},{"j":"↑自分↑↓じぶん↓が↑堅↑↓かた↓く↑誓↑↓ちか↓ったことは、どんなことがあっても↑実行↑↓じっこう↓しなければいけないよ。","e":"You've got to carry out your commitment at all costs."},{"j":"↑新↑↓しん↓↑社長↑↓しゃちょう↓は、↑会社↑↓かいしゃ↓の↑体質↑↓たいしつ↓を↑堅固↑↓けんご↓なものに↑作↑↓つく↓り↑上↑↓あ↓げた。","e":"The new boss has whipped the company into shape."},{"j":"↑彼↑↓かれ↓の↑態度↑↓たいど↓は↑軍人↑↓ぐんじん↓らしく↑堅苦↑↓かたくる↓しかった。","e":"His bearing was stiff and military."},{"j":"↑彼↑↓かれ↓はまったく↑堅↑↓かた↓い↑男↑↓おとこ↓だ。","e":"He is quite a clever man."},{"j":"↑彼↑↓かれ↓は↑堅↑↓かた↓く↑決心↑↓けっしん↓をしていたので↑我々↑↓われわれ↓は↑彼↑↓かれ↓を↑従↑↓したが↓わせることができなかった。","e":"He was determined, and we couldn't bend him."},{"j":"↑彼↑↓かれ↓は↑堅物↑↓かたぶつ↓だから、どうも↑息子↑↓むすこ↓が↑転職↑↓てんしょく↓するのにいい↑顔↑↓かお↓をしないんだよね。","e":"He's a really straight-laced guy, so he doesn't like the idea of his son changing jobs."},{"j":"↑彼↑↓かれ↓は↑口↑↓くち↓が↑堅↑↓かた↓い。","e":"He is a tight-lipped man."},{"j":"↑彼↑↓かれ↓は↑私↑↓わたし↓↑達↑↓たち↓に↑対↑↓たい↓して↑実↑↓じつ↓に↑堅苦↑↓かたくる↓しい。","e":"He is very formal with us."},{"j":"↑彼↑↓かれ↓は↑自分↑↓じぶん↓の↑神↑↓かみ↓を↑堅↑↓かた↓く↑信↑↓しん↓じていた。","e":"He had a firm belief in his God."},{"j":"↑彼女↑↓かのじょ↓の↑神↑↓かみ↓への↑信仰↑↓しんこう↓はとても↑堅↑↓かた↓い。","e":"Her belief in God is very firm."},{"j":"↑彼女↑↓かのじょ↓は↑堅↑↓かた↓いいすに↑座↑↓すわ↓った。","e":"She sat on a hard chair."}],"kdata":{"on":["ケン"],"kun":["かた.い","-がた.い"],"jlpt":1,"meanings":["strict","hard","solid","tough","tight","reliable"],"freq":1049,"comp":[["臤","土"]],"d":["樫","鰹","鏗","慳"],"t":1473},"c":{"meanings":["strict","hard","solid","tough","tight","reliable"],"on":["ケン"],"kun":["かた.い","-がた.い"]}}