{"jdata":[{"k_ele":[{"e":"妖精","p":true}],"r_ele":[{"r":"ようせい","p":true}],"sense":[{"gloss":"fairy, sprite, elf","pos":["n","adj-no"]}]},{"k_ele":[{"e":"妖怪","p":true}],"r_ele":[{"r":"ようかい","p":true}],"sense":[{"gloss":"ghost, apparition, phantom, spectre, specter, demon, monster, goblin, yōkai","pos":["n"]}]},{"k_ele":[{"e":"妖艶","p":true},{"e":"妖婉"}],"r_ele":[{"r":"ようえん","p":true}],"sense":[{"gloss":"fascinating, voluptuous, bewitching, captivating","pos":["adj-na","n"]}]},{"k_ele":[{"e":"妖魔"}],"r_ele":[{"r":"ようま"}],"sense":[{"gloss":"ghost, apparition","pos":["n"]}]},{"k_ele":[{"e":"妖しい"}],"r_ele":[{"r":"あやしい"}],"sense":[{"gloss":"mysterious, bewitching, alluring, enticing, enchanting","pos":["adj-i"],"x":["怪しい・あやしい・7"]}]},{"k_ele":[{"e":"妖術"}],"r_ele":[{"r":"ようじゅつ"}],"sense":[{"gloss":"black magic, black art, witchcraft, sorcery","pos":["n"]}]},{"k_ele":[{"e":"妖術者"}],"r_ele":[{"r":"ようじゅつしゃ"}],"sense":[{"gloss":"magician, sorcerer, sorceress","pos":["n"]}]},{"k_ele":[{"e":"面妖"}],"r_ele":[{"r":"めんよう"}],"sense":[{"gloss":"weird, strange, mysterious","pos":["adj-na","n"]}]},{"k_ele":[{"e":"妖女"}],"r_ele":[{"r":"ようじょ"}],"sense":[{"gloss":"enchantress, vamp","pos":["n"]}]},{"k_ele":[{"e":"妖気"}],"r_ele":[{"r":"ようき"}],"sense":[{"gloss":"ghostly air, weird air, unearthly atmosphere","pos":["n"]}]},{"k_ele":[{"e":"妖怪変化"}],"r_ele":[{"r":"ようかいへんげ"}],"sense":[{"gloss":"(animal making a) monstrous apparition","pos":["n","vs"]}],"m":["yoji"]},{"k_ele":[{"e":"妖婦"}],"r_ele":[{"r":"ようふ"}],"sense":[{"gloss":"enchantress, seductress, vamp","pos":["n"],"x":["バンプ・1"]}]},{"k_ele":[{"e":"妖婆"}],"r_ele":[{"r":"ようば"}],"sense":[{"gloss":"hag, old witch","pos":["n"]}]},{"k_ele":[{"e":"妖異"}],"r_ele":[{"r":"ようい"}],"sense":[{"gloss":"mysterious occurrence","pos":["n"]}]},{"k_ele":[{"e":"妖雲"}],"r_ele":[{"r":"よううん"}],"sense":[{"gloss":"ominous cloud","pos":["n"]}]},{"k_ele":[{"e":"狐狸妖怪"}],"r_ele":[{"r":"こりようかい"}],"sense":[{"gloss":"tricksters, deceivers, fey creatures, monsters, goblins","pos":["n"]}],"m":["yoji"]},{"k_ele":[{"e":"幻妖"}],"r_ele":[{"r":"げんよう"}],"sense":[{"gloss":"confusing people","pos":["n","vs"]},{"gloss":"magic","pos":["n","vs"]},{"gloss":"ghost, monster, etc., the true identity of which is unknown","pos":["n","vs"]}]},{"k_ele":[{"e":"妖術師"}],"r_ele":[{"r":"ようじゅつし"}],"sense":[{"gloss":"necromancer","pos":["n"]}]},{"k_ele":[{"e":"妖狐"}],"r_ele":[{"r":"ようこ"}],"sense":[{"gloss":"fox with supernatural powers, fox spirit","pos":["n"]}]},{"k_ele":[{"e":"歯の妖精"}],"r_ele":[{"r":"はのようせい"}],"sense":[{"gloss":"tooth fairy","pos":["exp","n"]}]},{"k_ele":[{"e":"妖刀"}],"r_ele":[{"r":"ようとう"}],"sense":[{"gloss":"bewitched sword, magical sword, demon sword","pos":["n"]}]},{"k_ele":[{"e":"天変地夭"},{"e":"天変地妖"}],"r_ele":[{"r":"てんぺんちよう"}],"sense":[{"gloss":"natural disaster","pos":["n"],"x":["天変地異"]}],"m":["arch"]},{"k_ele":[{"e":"妖力"}],"r_ele":[{"r":"ようりょく"},{"r":"ようりき"}],"sense":[{"gloss":"spirit power, magical power","pos":["n"]}],"m":["rare"]},{"k_ele":[{"e":"妖花"}],"r_ele":[{"r":"ようか"}],"sense":[{"gloss":"enchantingly beautiful flower, bewitching beauty","pos":["n"]}]},{"k_ele":[{"e":"妖言"}],"r_ele":[{"r":"およずれごと"}],"sense":[{"gloss":"groundless rumor (rumour), misleading rumor","pos":["n"]}],"m":["arch"]},{"k_ele":[{"e":"妖言"}],"r_ele":[{"r":"ようげん"}],"sense":[{"gloss":"dire prophecy that creates confusion","pos":["n"]}]},{"k_ele":[{"e":"大妖"}],"r_ele":[{"r":"たいよう"}],"sense":[{"gloss":"great demon, ghostly giant","pos":["n"]}]},{"k_ele":[{"e":"妖姫"}],"r_ele":[{"r":"ようき"}],"sense":[{"gloss":"ghostly, beautiful woman","pos":["n"]},{"gloss":"ghost of a beautiful woman","pos":["n"]}]},{"k_ele":[{"e":"妖邪"}],"r_ele":[{"r":"ようじゃ"}],"sense":[{"gloss":"evil intent, malice","pos":["n","adj-no"]}],"m":["arch"]},{"k_ele":[{"e":"妖氛"}],"r_ele":[{"r":"ようふん"}],"sense":[{"gloss":"ominous air, weird air, menacing atmosphere","pos":["n"],"x":["妖気"]}],"m":["arch"]},{"k_ele":[{"e":"妖鬼"}],"r_ele":[{"r":"ようき"}],"sense":[{"gloss":"ghost, apparition, phantom, spectre, specter, demon, monster, goblin","pos":["n"]}]},{"k_ele":[{"e":"妖精さん"}],"r_ele":[{"r":"ようせいさん"}],"sense":[{"gloss":"older employee who does not have much actual work","pos":["n"]}],"m":["joc"]}],"sdata":[{"j":"↑私↑↓わたし↓は↑妖精↑↓ようせい↓の↑役↑↓やく↓を↑演↑↓えん↓じた。","e":"I acted the part of a fairy."},{"j":"↑彼女↑↓かのじょ↓の↑足取↑↓あしど↓りは↑妖精↑↓ようせい↓のように↑軽↑↓かろ↓やかだった。","e":"Her footsteps were as light as a fairy's."},{"j":"↑彼女↑↓かのじょ↓は↑噂↑↓うわさ↓をふりまく↑妖精↑↓ようせい↓だ。","e":"She is a confirmed gossip."},{"j":"↑彼女↑↓かのじょ↓は↑妖精↑↓ようせい↓の↑役↑↓やく↓を↑演↑↓えん↓じた。","e":"She acted the part of a fairy."},{"j":"↑妖精↑↓ようせい↓は↑王子↑↓おうじ↓を↑猫↑↓ねこ↓に↑変↑↓か↓えた。","e":"The fairy changed the prince into a cat."},{"j":"↑妖精↑↓ようせい↓を↑信↑↓しん↓じてるの？","e":"Do you believe in fairies?"},{"j":"↑一匹↑↓いっぴき↓の↑妖怪↑↓ようかい↓がヨーロッパを↑徘徊↑↓はいかい↓している。↑共産↑↓きょうさん↓↑主義↑↓しゅぎ↓という↑妖怪↑↓ようかい↓が。","e":"A spectre is haunting Europe — the spectre of communism."},{"j":"↑妖精↑↓ようせい↓たちはサンタの↑小↑↓ちい↓さな↑助↑↓すけ↓っ↑人↑↓と↓です。","e":"Elves are Santa's little helpers."},{"j":"↑妖怪↑↓ようかい↓なんているわけないじゃないか。バカだな。","e":"Of course there's no such thing as yokai. You're such an idiot."},{"j":"メアリーは↑妖精↑↓ようせい↓なの。","e":"Mary is an elf."}],"kdata":{"on":["ヨウ"],"kun":["あや.しい","なま.めく","わざわ.い"],"meanings":["attractive","bewitching","calamity"],"freq":1964,"comp":[["夭","女"]],"jlpt":1,"t":580},"c":{"meanings":["attractive","bewitching","calamity"],"on":["ヨウ"],"kun":["あや.しい","なま.めく","わざわ.い"]}}