{"jdata":[{"k_ele":[{"e":"帰り","p":true},{"e":"還り"}],"r_ele":[{"r":"かえり","p":true}],"sense":[{"gloss":"return, coming back","pos":["n"]}]},{"k_ele":[{"e":"帰る","p":true},{"e":"還る"},{"e":"歸る","i":["sK"]},{"e":"復る","i":["sK"]}],"r_ele":[{"r":"かえる","p":true}],"sense":[{"gloss":"to return, to come home, to go home, to go back","pos":["v5r","vi"]},{"gloss":"to leave (of a guest, customer, etc.)","pos":["v5r","vi"]},{"gloss":"to get home, to get to home plate","pos":["v5r","vi"],"f":["baseb"]}]},{"k_ele":[{"e":"帰国","p":true}],"r_ele":[{"r":"きこく","p":true}],"sense":[{"gloss":"return to one's country","pos":["n","vs","vi"]},{"gloss":"return to one's hometown","pos":["n","vs","vi"],"m":["dated"]}]},{"k_ele":[{"e":"帰宅","p":true}],"r_ele":[{"r":"きたく","p":true}],"sense":[{"gloss":"returning home, going home, coming home, getting home","pos":["n","vs","vi"]}]},{"k_ele":[{"e":"復帰","p":true}],"r_ele":[{"r":"ふっき","p":true}],"sense":[{"gloss":"return, reversion, comeback, reinstatement","pos":["n","vs","vi"]},{"gloss":"carriage return","pos":["n"],"f":["comp"]}]},{"k_ele":[{"e":"帰還","p":true},{"e":"饋還","i":["rK"]}],"r_ele":[{"r":"きかん","p":true}],"sense":[{"gloss":"return (home), repatriation","pos":["n","vs","vi"]},{"gloss":"feedback (in an electronic circuit, biological system, etc.)","pos":["n","vs","vt"],"x":["フィードバック・2"]}]},{"k_ele":[{"e":"帰属","p":true}],"r_ele":[{"r":"きぞく","p":true}],"sense":[{"gloss":"belonging, ascription, attribution, imputation, possession, jurisdiction","pos":["n","vs","vi"]},{"gloss":"reversion, return, restoration","pos":["n","vs","vi"]}]},{"k_ele":[{"e":"帰り道","p":true},{"e":"帰り路"}],"r_ele":[{"r":"かえりみち","p":true}],"sense":[{"gloss":"the way back, the way home, return trip","pos":["n"]}]},{"k_ele":[{"e":"帰れ"}],"r_ele":[{"r":"かえれ"}],"sense":[{"gloss":"go home, get out","pos":["exp"]}]},{"k_ele":[{"e":"帰省","p":true}],"r_ele":[{"r":"きせい","p":true}],"sense":[{"gloss":"homecoming, returning home","pos":["n","vs","vi"]}]}],"sdata":[{"j":"↑明日↑↓あした↓↑帰↑↓かえ↓ったら↑電話↑↓でんわ↓します。","e":"I'll call them tomorrow when I come back."},{"j":"↑家↑↓いえ↓に↑帰↑↓かえ↓りましょうか。","e":"Why don't we go home?"},{"j":"↑君↑↓きみ↓は↑直↑↓ただ↓ちに↑家↑↓いえ↓へ↑帰↑↓かえ↓らなければならない。","e":"You must go home at once."},{"j":"↑君↑↓きみ↓はすぐに↑家↑↓いえ↓に↑帰↑↓かえ↓らなければいけません。","e":"You must go home at once."},{"j":"↑君↑↓きみ↓は↑自由↑↓じゆう↓に↑帰↑↓かえ↓っていいよ。","e":"You are free to go home."},{"j":"↑君↑↓きみ↓は↑私↑↓わたし↓が↑帰↑↓かえ↓るのを↑待↑↓ま↓ちさえすればよい。","e":"All you have to do is to wait for me to return."},{"j":"↑君↑↓きみ↓は↑九↑↓く↓↑時↑↓じ↓↑前↑↓まえ↓に↑帰↑↓かえ↓らなければならない。","e":"You must come back before nine o'clock."},{"j":"↑９↑↓く↓↑時↑↓じ↓↑前↑↓まえ↓に↑帰↑↓かえ↓らなければならない。","e":"You must come back before nine o'clock."},{"j":"↑君↑↓きみ↓は↑帰国↑↓きこく↓のことを↑友人↑↓ゆうじん↓に↑知↑↓し↓らせたのか。","e":"Did you inform your friends of your home-coming?"},{"j":"↑君↑↓きみ↓は↑暗↑↓くら↓くならないうちに↑家↑↓いえ↓に↑帰↑↓かえ↓るべきです。","e":"You should return home before it gets dark."}],"kdata":{"on":["キ"],"kun":["かえ.る","かえ.す","おく.る","とつ.ぐ"],"jlpt":4,"meanings":["homecoming","arrive at","lead to","result in"],"freq":504,"comp":[["刂","帚"]],"t":1058},"c":{"meanings":["homecoming","arrive at","lead to","result in"],"on":["キ"],"kun":["かえ.る","かえ.す","おく.る","とつ.ぐ"],"words":[{"word":"帰り","gloss":"return, coming back","p":"n"},{"word":"帰る","gloss":"to return, to come home, to go home, to go back","p":"v5r"},{"word":"帰国","gloss":"return to one's country","p":"n"}]}}