{"jdata":[{"k_ele":[{"e":"約束","p":true}],"r_ele":[{"r":"やくそく","p":true}],"sense":[{"gloss":"promise, agreement, arrangement, one's word, contract, pact, appointment, engagement, date","pos":["n","vs","vt"]},{"gloss":"convention, rule","pos":["n"]},{"gloss":"destiny, fate","pos":["n","vs","vt"]}]},{"k_ele":[{"e":"拘束","p":true}],"r_ele":[{"r":"こうそく","p":true}],"sense":[{"gloss":"restriction, restraint, binding, constraint","pos":["n","vs","vt"]}]},{"k_ele":[{"e":"束","p":true},{"e":"把"}],"r_ele":[{"r":"たば","p":true}],"sense":[{"gloss":"bundle, bunch, sheaf","pos":["n","n-suf","ctr"]}]},{"k_ele":[{"e":"束"}],"r_ele":[{"r":"つか"}],"sense":[{"gloss":"strut, short vertical post","pos":["n"]},{"gloss":"thickness (of a book minus the cover, a sheaf of paper, etc.)","pos":["n"]},{"gloss":"handbreadth, bundle","pos":["n"],"m":["arch"],"x":["束・そく"]}]},{"k_ele":[{"e":"束"}],"r_ele":[{"r":"そく"}],"sense":[{"gloss":"lattice","pos":["n","n-suf"],"f":["math"]},{"gloss":"counter for large bundles (e.g. 10 sheafs of rice, 200 sheets of calligraphy paper, 20 whistling arrows, 100 fish)","pos":["n","n-suf","ctr"]},{"gloss":"handbreadth (unit for measuring the length of arrows)","pos":["n","n-suf","ctr"]}]},{"k_ele":[{"e":"結束","p":true}],"r_ele":[{"r":"けっそく","p":true}],"sense":[{"gloss":"union, unity, solidarity","pos":["n","vs","vt","vi"]},{"gloss":"bundling, binding, tying","pos":["n","vs","vt","vi"]},{"gloss":"putting on (clothes, armour, etc.)","pos":["n","vs","vt","vi"],"m":["arch"]}]},{"k_ele":[{"e":"花束","p":true}],"r_ele":[{"r":"はなたば","p":true}],"sense":[{"gloss":"bunch of flowers, bouquet","pos":["n"]}]},{"k_ele":[{"e":"束縛","p":true}],"r_ele":[{"r":"そくばく","p":true}],"sense":[{"gloss":"restraint, restriction, fetters, yoke, shackles","pos":["n","vs","vt"]},{"gloss":"binding, confinement with rope","pos":["n","vs","vt"]}]},{"k_ele":[{"e":"収束","p":true}],"r_ele":[{"r":"しゅうそく","p":true}],"sense":[{"gloss":"conclusion, resolution, firming up (plans, etc.), coming together, returning to normal","pos":["n","vs","adj-no"]},{"gloss":"gathering and bundling","pos":["n","vs","adj-no"]},{"gloss":"convergence","pos":["n","vs","adj-no"],"f":["math"],"ant":["発散・4"]},{"gloss":"focusing (e.g. light), convergence","pos":["n","vs","adj-no"],"x":["集束"]}]},{"k_ele":[{"e":"つかの間","p":true},{"e":"束の間","p":true}],"r_ele":[{"r":"つかのま","p":true}],"sense":[{"gloss":"moment, brief space of time","pos":["exp","n","adj-no"]}]}],"sdata":[{"j":"↑約束↑↓やくそく↓するよ。","e":"I give you my word."},{"j":"↑君↑↓きみ↓は↑彼↑↓かれ↓が↑約束↑↓やくそく↓を↑守↑↓まも↓ると↑信↑↓しん↓じてよい。","e":"You can trust him to keep his word."},{"j":"↑君↑↓きみ↓は↑確↑↓たし↓かに↑約束↑↓やくそく↓を↑守↑↓まも↓る↑人↑↓ひと↓だ。","e":"He is, indeed, a man of his word."},{"j":"↑君↑↓きみ↓はそのロープをほどかないと↑約束↑↓やくそく↓しなさい。","e":"You must promise not to take the rope off."},{"j":"↑君↑↓きみ↓はあくまでも↑約束↑↓やくそく↓を↑守↑↓まも↓らなければならない。","e":"You must stick to your promise."},{"j":"↑君↑↓きみ↓の↑約束↑↓やくそく↓を↑当↑↓あ↓てにしている。","e":"I rest on your promise."},{"j":"↑君↑↓きみ↓に↑約束↑↓やくそく↓した３、０００ドルをあてにしてもいいよ。","e":"You can count on the $3,000 I have promised you."},{"j":"↑緊急↑↓きんきゅう↓の↑用事↑↓ようじ↓ができたので↑約束↑↓やくそく↓を↑取↑↓と↓り↑消↑↓け↓した。","e":"I canceled my appointment because of urgent business."},{"j":"↑急用↑↓きゅうよう↓ができたので↑約束↑↓やくそく↓をキャンセルした。","e":"I canceled my appointment because of urgent business."},{"j":"↑業者↑↓ぎょうしゃ↓が↑造花↑↓ぞうか↓の↑花束↑↓はなたば↓を↑届↑↓とど↓けて↑飾↑↓かざ↓っている。","e":"A delivery man is dropping off an arrangement of artificial flowers."}],"kdata":{"on":["ソク"],"kun":["たば","たば.ねる","つか","つか.ねる"],"jlpt":3,"meanings":["bundle","sheaf","ream","tie in bundles","govern","manage","control"],"freq":918,"comp":[["木","囗"]],"d":["速","頼","疎","勅","辣","剌","賴","竦","敕","柬","踈","涑","悚","捒","欶","觫","餗","鵣"],"s":"乗,東,垂","t":523},"c":{"meanings":["bundle","sheaf","ream","tie in bundles","govern","manage","control"],"on":["ソク"],"kun":["たば","たば.ねる","つか","つか.ねる"],"words":[{"word":"約束","gloss":"promise, agreement, arrangement, one's word, contract, pact, appointment, engagement, date","p":"n"},{"word":"拘束","gloss":"restriction, restraint, binding, constraint","p":"n"},{"word":"束","gloss":"bundle, bunch, sheaf","p":"n"}]}}