{"jdata":[{"k_ele":[{"e":"渥地"}],"r_ele":[{"r":"あくち"}],"sense":[{"gloss":"marshland","pos":["n"]}]},{"k_ele":[{"e":"優渥"}],"r_ele":[{"r":"ゆうあく"}],"sense":[{"gloss":"gracious","pos":["adj-na","n"]}]},{"k_ele":[{"e":"渥然"}],"r_ele":[{"r":"あくぜん"}],"sense":[{"gloss":"glossy","pos":["adj-t","adv-to"]}]}],"kdata":{"on":["アク"],"kun":["あつ.い","うるお.う"],"meanings":["kindness","moisten"],"freq":2257,"comp":[["屋","氵"]],"jlpt":0},"c":{"meanings":["kindness","moisten"],"on":["アク"],"kun":["あつ.い","うるお.う"],"words":[{"word":"渥地","gloss":"marshland","p":"n"},{"word":"優渥","gloss":"gracious","p":"adj-na"},{"word":"渥然","gloss":"glossy","p":"adj-t"}]}}