{"jdata":[{"k_ele":[{"e":"皓然"},{"e":"皎然"}],"r_ele":[{"r":"こうぜん"}],"sense":[{"gloss":"shining brightly, shining whitely","pos":["adj-t","adv-to"]}]},{"k_ele":[{"e":"皓々"},{"e":"皎々"},{"e":"晧々"},{"e":"皓皓"},{"e":"晧晧"},{"e":"皎皎"}],"r_ele":[{"r":"こうこう"},{"r":"きょうきょう"}],"sense":[{"gloss":"bright (esp. of the moon)","pos":["adj-t","adv-to"]},{"gloss":"broad and empty","pos":["adj-t","adv-to"]}]},{"k_ele":[{"e":"皓白"},{"e":"皎白","i":["sK"]}],"r_ele":[{"r":"こうはく"}],"sense":[{"gloss":"pure white","pos":["adj-no","n"]}],"m":["rare"]}],"kdata":{"on":["キョウ","コウ"],"kun":["きよ.い","しろ.い"],"meanings":["white","shining"],"comp":[["白","交"]],"freq":4413},"c":{"meanings":["white","shining"],"on":["キョウ","コウ"],"kun":["きよ.い","しろ.い"],"words":[{"word":"皎然","gloss":"shining brightly, shining whitely","p":"adj-t"},{"word":"皎々","gloss":"bright (esp. of the moon)","p":"adj-t"},{"word":"皎白","gloss":"pure white","p":"adj-no"}]}}