{"jdata":[{"k_ele":[{"e":"矯正","p":true},{"e":"きょう正","i":["sK"]}],"r_ele":[{"r":"きょうせい","p":true}],"sense":[{"gloss":"correction (of a fault, defect, flaw, etc.), remedy, rectification, redress, reform, straightening (of teeth)","pos":["n","vs","vt"]}]},{"k_ele":[{"e":"奇矯"}],"r_ele":[{"r":"ききょう"}],"sense":[{"gloss":"eccentric","pos":["adj-na","n"]}]},{"k_ele":[{"e":"矯める"}],"r_ele":[{"r":"ためる"}],"sense":[{"gloss":"to straighten, to correct, to cure","pos":["v1","vt"]},{"gloss":"to falsify","pos":["v1","vt"]}]},{"k_ele":[{"e":"矯め直す"},{"e":"矯めなおす"}],"r_ele":[{"r":"ためなおす"}],"sense":[{"gloss":"to set up again, to correct, to cure","pos":["v5s"]}]},{"k_ele":[{"e":"矯激"}],"r_ele":[{"r":"きょうげき"}],"sense":[{"gloss":"radical, extreme, eccentric","pos":["adj-na","n"]}]},{"k_ele":[{"e":"矯風"}],"r_ele":[{"r":"きょうふう"}],"sense":[{"gloss":"reform of morals","pos":["n"]}]},{"k_ele":[{"e":"歯牙矯正術"}],"r_ele":[{"r":"しがきょうせいじゅつ"}],"sense":[{"gloss":"orthodontia","pos":["n"]}]},{"k_ele":[{"e":"歯列矯正"}],"r_ele":[{"r":"しれつきょうせい"}],"sense":[{"gloss":"orthodontia, orthodontics","pos":["n"]}]},{"k_ele":[{"e":"矯めつ眇めつ"}],"r_ele":[{"r":"ためつすがめつ"}],"sense":[{"gloss":"scrutiny, scanning, taking a good look","pos":["exp","vs","adv"]}]},{"k_ele":[{"e":"矯正視力"}],"r_ele":[{"r":"きょうせいしりょく"}],"sense":[{"gloss":"corrected eyesight","pos":["n"]}]},{"k_ele":[{"e":"枝を矯める"}],"r_ele":[{"r":"えだをためる"}],"sense":[{"gloss":"to straighten a branch","pos":["exp","v1"]}]},{"k_ele":[{"e":"奇矯な癖"}],"r_ele":[{"r":"ききょうなへき"}],"sense":[{"gloss":"eccentric habit","pos":["n"]}]},{"k_ele":[{"e":"矯飾"}],"r_ele":[{"r":"きょうしょく"}],"sense":[{"gloss":"affectation, pretense, pretence","pos":["n","vs","vt"]}]},{"k_ele":[{"e":"不正を矯める"}],"r_ele":[{"r":"ふせいをためる"}],"sense":[{"gloss":"to redress injustice","pos":["exp","v1"]}]},{"k_ele":[{"e":"視力矯正手術"}],"r_ele":[{"r":"しりょくきょうせいしゅじゅつ"}],"sense":[{"gloss":"vision correcting surgery","pos":["n"]}]},{"k_ele":[{"e":"矯角殺牛"}],"r_ele":[{"r":"きょうかくさつぎゅう"}],"sense":[{"gloss":"trying to straighten the horns of a bull, and killing it in the process, trying to correct a small defect and ruining the whole thing, the cure is worse than the disease","pos":["exp"]}],"m":["yoji"]},{"k_ele":[{"e":"矯味剤"}],"r_ele":[{"r":"きょうみざい"}],"sense":[{"gloss":"taste masking agent, flavoring substance","pos":["n"]}]},{"k_ele":[{"e":"矯正職員"}],"r_ele":[{"r":"きょうせいしょくいん"}],"sense":[{"gloss":"correctional officer, corrections officer","pos":["n"],"x":["刑務官"]}]},{"k_ele":[{"e":"歯列矯正器"}],"r_ele":[{"r":"しれつきょうせいき"}],"sense":[{"gloss":"(orthodontic) braces","pos":["n"]}]},{"k_ele":[{"e":"縮毛矯正"}],"r_ele":[{"r":"しゅくもうきょうせい"}],"sense":[{"gloss":"hair straightening","pos":["n","vs"]}]},{"k_ele":[{"e":"角を矯めて牛を殺す"}],"r_ele":[{"r":"つのをためてうしをころす"}],"sense":[{"gloss":"to throw the baby out with the bath water, to strain at a gnat and swallow a camel, to obsess over insignificant details and miss the larger point, to straighten the horns and kill the cow","pos":["exp","v5s"]}],"m":["id"]},{"k_ele":[{"e":"矯正施設"}],"r_ele":[{"r":"きょうせいしせつ"}],"sense":[{"gloss":"correctional facility (for juveniles), juvenile detention centre (center), reformatory","pos":["n"]}]},{"k_ele":[{"e":"裏側矯正"}],"r_ele":[{"r":"うらがわきょうせい"}],"sense":[{"gloss":"lingual braces (dentistry)","pos":["n"]}]},{"k_ele":[{"e":"矯正歯科医"}],"r_ele":[{"r":"きょうせいしかい"}],"sense":[{"gloss":"orthodontist","pos":["n"],"f":["med"]}]},{"k_ele":[{"e":"歯科矯正学"}],"r_ele":[{"r":"しかきょうせいがく"}],"sense":[{"gloss":"orthodontics, orthodontia","pos":["n"]}]},{"k_ele":[{"e":"矯正歯科"}],"r_ele":[{"r":"きょうせいしか"}],"sense":[{"gloss":"orthodontics","pos":["n"],"f":["med"]}]},{"k_ele":[{"e":"過剰矯正"}],"r_ele":[{"r":"かじょうきょうせい"}],"sense":[{"gloss":"hypercorrection","pos":["n"],"f":["ling"],"x":["過剰修正"]}]},{"k_ele":[{"e":"舌側矯正"}],"r_ele":[{"r":"ぜっそくきょうせい"}],"sense":[{"gloss":"lingual orthodontics (e.g. braces)","pos":["n"],"f":["med"]}]},{"k_ele":[{"e":"矯正院"}],"r_ele":[{"r":"きょうせいいん"}],"sense":[{"gloss":"reformatory, house of correction","pos":["n"],"x":["少年院"]}],"m":["obs"]}],"sdata":[{"j":"↑眼鏡↑↓めがね↓をかければ↑君↑↓きみ↓の↑視力↑↓しりょく↓は↑矯正↑↓きょうせい↓されるだろう。","e":"Wearing glasses should correct your vision."},{"j":"↑悪↑↓わる↓すぎてとても↑矯正↑↓きょうせい↓は↑無理↑↓むり↓だ。","e":"He is bad beyond correction."},{"j":"↑歯↑↓し↓↑列↑↓れつ↓↑矯正↑↓きょうせい↓をお↑願↑↓ねが↓いしたいのですが。","e":"I think I need braces."},{"j":"↑歯↑↓は↓↑列↑↓れつ↓↑矯正↑↓きょうせい↓についてご↑相談↑↓そうだん↓したいのですが。","e":"I'd like to have a consultation about getting braces."},{"j":"↑彼↑↓かれ↓には↑矯正↑↓きょうせい↓が↑必要↑↓ひつよう↓である。","e":"He needs discipline."},{"j":"↑娘↑↓むすめ↓の↑歯↑↓は↓↑列↑↓れつ↓を↑矯正↑↓きょうせい↓していただきたいのです。","e":"I'd like to have her teeth straightened."},{"j":"↑娘↑↓むすめ↓は↑歯↑↓は↓を↑矯正↑↓きょうせい↓↑中↑↓ちゅう↓です。","e":"My daughter has braces."},{"j":"↑強↑↓つよ↓い↑乱視↑↓らんし↓はコンタクトレンズのほうが↑矯正↑↓きょうせい↓できます。","e":"Contact lenses are more able to correct strong astigmatism."},{"j":"↑歯並↑↓はなら↓びがガタガタで↑格好↑↓かっこう↓↑悪↑↓わる↓いから、↑矯正↑↓きょうせい↓しようと↑思↑↓おも↓う。","e":"My teeth are all misaligned, so I'm thinking I might get some braces to try and correct them."},{"j":"↑歯↑↓は↓の↑矯正↑↓きょうせい↓をしたいんです。","e":"I would like to have my teeth straightened."}],"kdata":{"on":["キョウ"],"kun":["た.める"],"jlpt":1,"meanings":["reform","rectify","straighten","correct","cure","control","pretend","falsify"],"freq":2105,"comp":[["喬","矢"]],"t":2187},"c":{"meanings":["reform","rectify","straighten","correct","cure","control","pretend","falsify"],"on":["キョウ"],"kun":["た.める"]}}