{"jdata":[{"k_ele":[{"e":"種蒔き"},{"e":"種まき"},{"e":"種蒔"}],"r_ele":[{"r":"たねまき"}],"sense":[{"gloss":"sowing seeds, planting seeds, scattering seeds","pos":["n","vs"]}]},{"k_ele":[{"e":"遅まきながら"},{"e":"遅蒔きながら"},{"e":"晩蒔きながら"}],"r_ele":[{"r":"おそまきながら"}],"sense":[{"gloss":"belatedly","pos":["exp"],"x":["遅ればせながら"]}]},{"k_ele":[{"e":"蒔絵","p":true}],"r_ele":[{"r":"まきえ","p":true}],"sense":[{"gloss":"gold or silver lacquer, lacquer decoration sprinkled with metal powder","pos":["n"]}]},{"k_ele":[{"e":"豆まき","p":true},{"e":"豆撒き"},{"e":"豆蒔き"}],"r_ele":[{"r":"まめまき","p":true}],"sense":[{"gloss":"sowing beans (or pulses, etc.)","pos":["n","vs"]},{"gloss":"scattering parched beans (to drive out evil spirits)","pos":["n","vs"],"x":["節分・1"]}]},{"k_ele":[{"e":"麦蒔"}],"r_ele":[{"r":"むぎまき"}],"sense":[{"gloss":"wheat planting","pos":["n","vs"]}]},{"k_ele":[{"e":"ばら撒く","p":true},{"e":"ばら蒔く","i":["rK"]},{"e":"散蒔く","p":true,"i":["rK"]},{"e":"散播く","i":["rK"]}],"r_ele":[{"r":"ばらまく","p":true}],"sense":[{"gloss":"to scatter, to disseminate (e.g. a rumor), to spread (e.g. germs), to broadcast","pos":["v5k","vt"]},{"gloss":"to distribute widely (e.g. leaflets), to hand out freely, to spend recklessly","pos":["v5k","vt"]}],"m":["uk"]},{"k_ele":[{"e":"遅まき"},{"e":"遅蒔き"},{"e":"晩蒔き"}],"r_ele":[{"r":"おそまき"}],"sense":[{"gloss":"sowing late","pos":["n"],"ant":["早まき・はやまき"]},{"gloss":"doing late","pos":["n"],"x":["遅まきながら・おそまきながら"]}]},{"k_ele":[{"e":"春まき"},{"e":"春蒔き"}],"r_ele":[{"r":"はるまき"}],"sense":[{"gloss":"sowing in spring","pos":["n","adj-no"]}]},{"k_ele":[{"e":"秋まき"},{"e":"秋蒔き"}],"r_ele":[{"r":"あきまき"}],"sense":[{"gloss":"autumn sowing, fall sowing","pos":["n","vs","adj-no"]}]},{"k_ele":[{"e":"蒔き付け"}],"r_ele":[{"r":"まきつけ"}],"sense":[{"gloss":"sowing (seeds)","pos":["n"]}]}],"sdata":[{"j":"ジョニーは４６↑年間↑↓ねんかん↓りんごの↑種子↑↓しゅし↓を↑蒔↑↓ま↓き↑付↑↓づ↓けた。","e":"Johnny kept planting apple seeds for 46 years."},{"j":"↑蒔↑↓ま↓かぬ↑種↑↓しゅ↓は↑生↑↓は↓えない。","e":"You must sow before you can reap."},{"j":"↑蒔↑↓ま↓かぬ↑種↑↓たね↓は↑生↑↓は↓えぬ。","e":"Seeds unsown do not grow."},{"j":"↑農夫↑↓のうふ↓が↑畑↑↓はたけ↓に↑種↑↓たね↓を↑蒔↑↓ま↓いている。","e":"The farmer is scattering seeds over the field."},{"j":"↑農民↑↓のうみん↓が↑穀物↑↓こくもつ↓の↑種↑↓たね↓を↑蒔↑↓ま↓いた。","e":"The peasant scattered the seeds of grain."},{"j":"↑蒔↑↓ま↓かぬ↑種↑↓たね↓は↑生↑↓は↓えぬ。","e":"No autumn fruit without spring blossom."},{"j":"↑蒔↑↓ま↓かぬ↑種↑↓たね↓は↑生↑↓は↓えぬ。","e":"You cannot make an omelet without breaking eggs."},{"j":"↑蒔↑↓ま↓かぬ↑種↑↓たね↓は↑生↑↓は↓えぬ。","e":"You can't make an omelette without breaking eggs."},{"j":"↑蒔↑↓ま↓かぬ↑種↑↓たね↓は↑生↑↓は↓えぬ。","e":"You can't make an omelet without breaking eggs."},{"j":"↑蒔↑↓ま↓かぬ↑種↑↓たね↓は↑生↑↓は↓えぬ。","e":"If you don't plant the seeds, they won't grow."}],"kdata":{"on":["シ","ジ"],"kun":["う.える","ま.く"],"meanings":["sow (seeds)"],"freq":2368,"comp":[["艹","時"]],"jlpt":0},"c":{"meanings":["sow (seeds)"],"on":["シ","ジ"],"kun":["う.える","ま.く"],"words":[{"word":"種蒔き","gloss":"sowing seeds, planting seeds, scattering seeds","p":"n"},{"word":"遅蒔きながら","gloss":"belatedly","p":"exp"},{"word":"蒔絵","gloss":"gold or silver lacquer, lacquer decoration sprinkled with metal powder","p":"n"}]}}