{"jdata":[{"k_ele":[{"e":"蔵人"},{"e":"藏人"}],"r_ele":[{"r":"くろうど"},{"r":"くらんど"},{"r":"くらびと"}],"sense":[{"gloss":"keeper of imperial archives","pos":["n"]},{"gloss":"worker skilled in the brewing of sake or soy sauce","pos":["n"]}]},{"k_ele":[{"e":"西蔵"},{"e":"西藏","i":["oK"]}],"r_ele":[{"r":"せいぞう"}],"sense":[{"gloss":"Tibet","pos":["n"],"x":["チベット"]}],"m":["obs"]}],"kdata":{"on":["ゾウ","ソウ"],"kun":["くら","おさ.める","かく.れる"],"meanings":["hide","own","have","possess"],"freq":2407,"comp":[["臧","艹"]],"d":["臟"],"jlpt":0,"s":["蔵"]},"c":{"meanings":["hide","own","have","possess"],"on":["ゾウ","ソウ"],"kun":["くら","おさ.める","かく.れる"]}}