{"jdata":[{"k_ele":[{"e":"衰退","p":true},{"e":"衰頽","i":["rK"]}],"r_ele":[{"r":"すいたい","p":true}],"sense":[{"gloss":"decline, degeneration, decay, waning, ebbing","pos":["n","vs","vi"]}]},{"k_ele":[{"e":"衰え","p":true}],"r_ele":[{"r":"おとろえ","p":true}],"sense":[{"gloss":"weakening, emaciation, decline","pos":["n"]}]},{"k_ele":[{"e":"衰弱","p":true}],"r_ele":[{"r":"すいじゃく","p":true}],"sense":[{"gloss":"weakness, debility, breakdown, prostration","pos":["n","vs","vi","adj-no"]}]},{"k_ele":[{"e":"減衰","p":true}],"r_ele":[{"r":"げんすい","p":true}],"sense":[{"gloss":"attenuation, damping, decay","pos":["n","vs","vi"]}]},{"k_ele":[{"e":"衰える","p":true}],"r_ele":[{"r":"おとろえる","p":true}],"sense":[{"gloss":"to become weak, to decline, to wear, to abate, to decay, to wither, to waste away","pos":["v1","vi"],"ant":["栄える"]}]},{"k_ele":[{"e":"盛衰","p":true}],"r_ele":[{"r":"せいすい","p":true}],"sense":[{"gloss":"rise and fall, ups and downs, welfare, vicissitudes","pos":["n"]}]},{"k_ele":[{"e":"栄枯盛衰"}],"r_ele":[{"r":"えいこせいすい"}],"sense":[{"gloss":"ups and downs of life, vicissitudes of fortune","pos":["n"]}],"m":["yoji"]},{"k_ele":[{"e":"老衰","p":true}],"r_ele":[{"r":"ろうすい","p":true}],"sense":[{"gloss":"senility, senile decay, infirmity (through age)","pos":["n","vs","vi","adj-no"]}]},{"k_ele":[{"e":"減衰器"}],"r_ele":[{"r":"げんすいき"}],"sense":[{"gloss":"attenuator","pos":["n"]}]},{"k_ele":[{"e":"古び衰える","p":true}],"r_ele":[{"r":"ふるびおとろえる","p":true}],"sense":[{"gloss":"to waste away","pos":["v1"]}]}],"sdata":[{"j":"↑近年↑↓きんねん↓↑多↑↓おお↓くのそれぞれの↑地方↑↓ちほう↓の↑伝統↑↓でんとう↓が↑衰微↑↓すいび↓してきている。","e":"Many local traditions have fallen into decay in recent years."},{"j":"↑記憶↑↓きおく↓↑力↑↓りょく↓が↑衰↑↓おとろ↓えました。","e":"My memory is failing."},{"j":"↑簡潔↑↓かんけつ↓に↑言↑↓い↓うと、ホブボームの↑論点↑↓ろんてん↓は２０↑世紀↑↓せいき↓の↑歴史↑↓れきし↓は↑文化↑↓ぶんか↓↑衰退↑↓すいたい↓の↑歴史↑↓れきし↓であるということだ。","e":"Briefly stated, Hobsbawm's thesis is that the history of the twentieth century is that of the decline of civilization."},{"j":"↑栄枯盛衰↑↓えいこせいすい↓は↑世↑↓よ↓の↑習↑↓なら↓い。","e":"A man's life has its ups and downs."},{"j":"４７５↑年↑↓ねん↓はローマ↑帝国↑↓ていこく↓の「↑衰退↑↓すいたい↓」を↑示↑↓しめ↓す↑年↑↓とし↓ではあっても、「↑滅亡↑↓めつぼう↓」を↑意味↑↓いみ↓する↑年↑↓とし↓ではありません。","e":"Although 475AD is the year that shows the 'decline' of the Roman Empire, it is not the year of its 'fall'."},{"j":"その↑衰退↑↓すいたい↓はざっと１９５０↑年代↑↓ねんだい↓までさかのぼる↑事↑↓こと↓が↑出来↑↓でき↓る。","e":"The decline can be traced to the 1950s."},{"j":"その↑炎↑↓ほのお↓は↑衰↑↓おとろ↓え↑始↑↓はじ↓めた。","e":"The flame has begun to fade."},{"j":"そいつは↑衰退↑↓すいたい↓のレトリックというものだ。","e":"But it's the rhetoric of failure."},{"j":"じきにその↑衰弱↑↓すいじゃく↓は↑回復↑↓かいふく↓しますよ。","e":"You will recover from your weakness soon."},{"j":"ジェーンはもっと↑休憩↑↓きゅうけい↓をとらないと、↑神経↑↓しんけい↓↑衰弱↑↓すいじゃく↓になるかもしれない。","e":"If Jane does not rest more, she may have a nervous breakdown."}],"kdata":{"on":["スイ"],"kun":["おとろ.える"],"jlpt":1,"meanings":["decline","wane","weaken"],"freq":1432,"comp":[["哀","一"]],"d":["簑","蓑","榱","縗"],"s":"衷,哀","t":1167},"c":{"meanings":["decline","wane","weaken"],"on":["スイ"],"kun":["おとろ.える"],"words":[{"word":"衰退","gloss":"decline, degeneration, decay, waning, ebbing","p":"n"},{"word":"衰え","gloss":"weakening, emaciation, decline","p":"n"},{"word":"衰弱","gloss":"weakness, debility, breakdown, prostration","p":"n"}]}}