{"jdata":[{"k_ele":[{"e":"追加","p":true}],"r_ele":[{"r":"ついか","p":true}],"sense":[{"gloss":"addition, supplement, appending, appendix","pos":["n","vs","vt","adj-no"]}]},{"k_ele":[{"e":"追求","p":true}],"r_ele":[{"r":"ついきゅう","p":true}],"sense":[{"gloss":"pursuit (of a goal, ideal, etc.), search, chase, seeking after","pos":["n","vs","vt"]}]},{"k_ele":[{"e":"追及","p":true}],"r_ele":[{"r":"ついきゅう","p":true}],"sense":[{"gloss":"investigation (e.g. into someone's guilt), questioning, pressing, hounding, pinning down","pos":["n","vs","vt"]},{"gloss":"catching up, overtaking","pos":["n","vs","vt"]}]},{"k_ele":[{"e":"追跡","p":true}],"r_ele":[{"r":"ついせき","p":true}],"sense":[{"gloss":"chase, pursuit, tracking, stalking","pos":["n","vs","vt","adj-no"]},{"gloss":"following up, tracing","pos":["n","vs","vt","adj-no"]}]},{"k_ele":[{"e":"追悼","p":true}],"r_ele":[{"r":"ついとう","p":true}],"sense":[{"gloss":"mourning","pos":["n","vs","vt"]}]},{"k_ele":[{"e":"追う","p":true},{"e":"逐う"}],"r_ele":[{"r":"おう","p":true}],"sense":[{"gloss":"to chase, to run after, to pursue, to follow after","pos":["v5u","vt"]},{"gloss":"to follow (a set order, a trend, etc.)","pos":["v5u","vt"]},{"gloss":"to drive out, to get rid of, to oust, to expel","pos":["v5u","vt"]},{"gloss":"to drive (e.g. a herd)","pos":["v5u","vt"]},{"gloss":"to be pressed (e.g. for time)","pos":["v5u","vt"]}]},{"k_ele":[{"e":"追放","p":true}],"r_ele":[{"r":"ついほう","p":true}],"sense":[{"gloss":"exile, banishment, eviction, deportation, purge, expulsion, ousting","pos":["n","vs","vt"]},{"gloss":"elimination (e.g. of poverty), removal","pos":["n","vs","vt"]}]},{"k_ele":[{"e":"追記"}],"r_ele":[{"r":"ついき"}],"sense":[{"gloss":"PS, postscript","pos":["n","vs","vt"]},{"gloss":"appending, addition (esp. of data, information)","pos":["n","vs","vt"]}]},{"k_ele":[{"e":"押っ"},{"e":"追っ"}],"r_ele":[{"r":"おっ"}],"sense":[{"gloss":"vigorously ..., suddenly ...","pos":["pref"]}],"m":["uk"]},{"k_ele":[{"e":"追伸","p":true},{"e":"追申","i":["rK"]}],"r_ele":[{"r":"ついしん","p":true}],"sense":[{"gloss":"postscript, post scriptum, PS, P.S.","pos":["n"]}]}],"sdata":[{"j":"もしスペンサーが↑文↑↓ぶん↓を↑足↑↓た↓して↑訳↑↓やく↓し↑続↑↓つづ↓けなければ、↑他↑↓た↓の↑貢献↑↓こうけん↓↑者↑↓しゃ↓がきっと↑彼↑↓かれ↓を↑追↑↓お↓い↑抜↑↓ぬ↓くだろう。","e":"If Spenser doesn't keep adding and translating sentences, the other contributors will surely surpass him."},{"j":"↑君↑↓きみ↓はクラスのみんなに↑追↑↓お↓いつくために、↑一生懸命↑↓いっしょうけんめい↓↑勉強↑↓べんきょう↓しなくてはならない。","e":"You have to study hard to catch up with your class."},{"j":"↑君↑↓きみ↓がどんなに↑速↑↓はや↓く↑歩↑↓ある↓いても、↑彼↑↓かれ↓には↑追↑↓お↓いつけません。","e":"However fast you may walk, you can't catch up with him."},{"j":"↑金曜日↑↓きんようび↓↑締↑↓し↓め↑切↑↓き↓りのプロジェクトに↑追↑↓お↓われています。","e":"I'm tied up with a project that is due Friday."},{"j":"↑供給↑↓きょうきゅう↓がまもなく↑需要↑↓じゅよう↓に↑追↑↓お↓いつくでしょう。","e":"Supply will soon overtake demand."},{"j":"そして↑彼↑↓かれ↓は↑牛↑↓うし↓や↑羊↑↓ひつじ↓も↑皆↑↓みな↓、↑宮↑↓みや↓から↑追↑↓お↓いだした。","e":"And he chased the cattle, the sheep, and the people out of the temple."},{"j":"↑急↑↓いそ↓げば↑彼↑↓かれ↓に↑追↑↓お↓いつくでしょう。","e":"If you hurry, you'll catch up with him."},{"j":"↑急↑↓いそ↓ぎなさい。さもないと↑彼↑↓かれ↓に↑追↑↓お↓いつけないでしょう。","e":"Hurry up, or you won't catch up with him."},{"j":"↑会議↑↓かいぎ↓で↑川添↑↓かわぞえ↓さんの↑追及↑↓ついきゅう↓を↑受↑↓う↓けて↑冷↑↓ひ↓や↑汗↑↓あせ↓ものだったよ。","e":"When Kawazoe pinned me down at the meeting, I broke out in a cold sweat."},{"j":"↑我々↑↓われわれ↓は↑彼↑↓かれ↓を↑国外↑↓こくがい↓に↑追放↑↓ついほう↓した。","e":"We banished him from the country."}],"kdata":{"on":["ツイ"],"kun":["お.う"],"jlpt":3,"meanings":["chase","drive away","follow","pursue","meanwhile"],"freq":411,"comp":[["𠂤","辶"]],"d":["槌","鎚","縋","搥","磓"],"s":"過","t":965},"c":{"meanings":["chase","drive away","follow","pursue","meanwhile"],"on":["ツイ"],"kun":["お.う"],"words":[{"word":"追加","gloss":"addition, supplement, appending, appendix","p":"n"},{"word":"追求","gloss":"pursuit (of a goal, ideal, etc.), search, chase, seeking after","p":"n"},{"word":"追及","gloss":"investigation (e.g. into someone's guilt), questioning, pressing, hounding, pinning down","p":"n"}]}}