{"jdata":[{"k_ele":[{"e":"鎮圧","p":true}],"r_ele":[{"r":"ちんあつ","p":true}],"sense":[{"gloss":"suppression (of a riot, revolt, etc.), repression, putting down, quelling","pos":["n","vs","vt"]}]},{"k_ele":[{"e":"鎮座","p":true}],"r_ele":[{"r":"ちんざ","p":true}],"sense":[{"gloss":"enshrinement","pos":["n","vs","vi"]}]},{"k_ele":[{"e":"鎮静","p":true}],"r_ele":[{"r":"ちんせい","p":true}],"sense":[{"gloss":"calm, quiet, tranquility, tranquillity, appeasement, pacification","pos":["n","vs","vt","vi","adj-no"],"x":["沈静・ちんせい"]}]},{"k_ele":[{"e":"地鎮祭","p":true}],"r_ele":[{"r":"じちんさい","p":true}],"sense":[{"gloss":"ceremony for purifying a building site (before building commences), ground-breaking ceremony","pos":["n"],"f":["Shinto"]}]},{"k_ele":[{"e":"重鎮","p":true}],"r_ele":[{"r":"じゅうちん","p":true}],"sense":[{"gloss":"leader, authority, mainstay","pos":["n"]}]},{"k_ele":[{"e":"鎮魂","p":true}],"r_ele":[{"r":"ちんこん","p":true},{"r":"たましずめ"}],"sense":[{"gloss":"repose of a soul","pos":["n","vs","vt"]},{"gloss":"ceremony for the repose of a departed soul","pos":["n"]}]},{"k_ele":[{"e":"静める","p":true},{"e":"鎮める","p":true}],"r_ele":[{"r":"しずめる","p":true}],"sense":[{"gloss":"to quiet (a child, crowd, etc.), to quieten, to make quiet","pos":["v1","vt"]},{"gloss":"to calm (one's nerves, excitement, etc.), to compose (oneself), to appease (someone's anger), to pacify, to settle (e.g. discord)","pos":["v1","vt"]},{"gloss":"to suppress (a rebellion, riot, fire, etc.), to quell, to put down, to get under control","pos":["v1","vt"]},{"gloss":"to relieve (a cough, pain, etc.), to soothe, to alleviate, to ease","pos":["v1","vt"]},{"gloss":"to appease (a spirit, soul, etc.), to pacify, to soothe","pos":["v1","vt"]}]},{"k_ele":[{"e":"鎮守","p":true},{"e":"鎮主","i":["rK"]}],"r_ele":[{"r":"ちんじゅ","p":true}],"sense":[{"gloss":"local Shinto deity, tutelary god","pos":["n"]}]},{"k_ele":[{"e":"鎮火","p":true}],"r_ele":[{"r":"ちんか","p":true}],"sense":[{"gloss":"extinguishing, dying out (of a fire), putting out","pos":["n","vs","vt","vi"]}]},{"k_ele":[{"e":"鎮痛剤","p":true}],"r_ele":[{"r":"ちんつうざい","p":true}],"sense":[{"gloss":"analgesic, painkiller, sedative, tranquilizer, tranquiliser","pos":["n"]}]},{"k_ele":[{"e":"静まる","p":true},{"e":"鎮まる","p":true}],"r_ele":[{"r":"しずまる","p":true}],"sense":[{"gloss":"to become quiet, to quiet down, to quieten down","pos":["v5r","vi"]},{"gloss":"to calm down, to die down, to subside, to abate, to be suppressed","pos":["v5r","vi"]}]},{"k_ele":[{"e":"鎮定","p":true}],"r_ele":[{"r":"ちんてい","p":true}],"sense":[{"gloss":"suppression (e.g. of a rebellion), pacification","pos":["n","vs","vt","vi"]}],"m":["hist"]},{"k_ele":[{"e":"鎮"}],"r_ele":[{"r":"ちん"},{"r":"しず","i":["ok"]}],"sense":[{"gloss":"a weight","pos":["n"],"f":["Buddh"],"m":["arch"]},{"gloss":"temple supervisor","pos":["n"]},{"gloss":"town (of China)","pos":["n"]}]},{"k_ele":[{"e":"鎮痛"}],"r_ele":[{"r":"ちんつう"}],"sense":[{"gloss":"pain relief, killing pain","pos":["n","adj-no","vs","vt","vi"]}]},{"k_ele":[{"e":"鎮め"}],"r_ele":[{"r":"しずめ"}],"sense":[{"gloss":"controlling, suppressing, quelling","pos":["n"]}]},{"k_ele":[{"e":"千木"},{"e":"知木"},{"e":"鎮木"}],"r_ele":[{"r":"ちぎ"}],"sense":[{"gloss":"ornamental crossed rafter ends on shrine gables","pos":["n"]}]},{"k_ele":[{"e":"鎮魂ミサ曲"}],"r_ele":[{"r":"ちんこんミサきょく"}],"sense":[{"gloss":"Requiem Mass","pos":["n"]}]},{"k_ele":[{"e":"鎮魂帰神"}],"r_ele":[{"r":"ちんこんきしん"}],"sense":[{"gloss":"return to the divine through spiritual quietude","pos":["n"]}]},{"k_ele":[{"e":"鎮魂曲"}],"r_ele":[{"r":"ちんこんきょく"}],"sense":[{"gloss":"requiem","pos":["n"]}]},{"k_ele":[{"e":"鎮静剤"}],"r_ele":[{"r":"ちんせいざい"}],"sense":[{"gloss":"sedative, tranquilizer, tranquiliser","pos":["n"]}]},{"k_ele":[{"e":"鎮痛性"}],"r_ele":[{"r":"ちんつうせい"}],"sense":[{"gloss":"analgesic","pos":["adj-na"]}]},{"k_ele":[{"e":"鎮痛薬"}],"r_ele":[{"r":"ちんつうやく"}],"sense":[{"gloss":"analgesic","pos":["n"]}]},{"k_ele":[{"e":"武漢三鎮"}],"r_ele":[{"r":"ぶかんさんちん"}],"sense":[{"gloss":"the three Wuhan Cities","pos":["n"]}]},{"k_ele":[{"e":"鎮守の杜"},{"e":"鎮守の森"}],"r_ele":[{"r":"ちんじゅのもり"}],"sense":[{"gloss":"grove of the village shrine","pos":["n"]}]},{"k_ele":[{"e":"文鎮"}],"r_ele":[{"r":"ぶんちん"}],"sense":[{"gloss":"paperweight","pos":["n"]}]},{"k_ele":[{"e":"鎮魂曲歌"}],"r_ele":[{"r":"ちんこんきょくか"}],"sense":[{"gloss":"(sung) requiem","pos":["n"]}]},{"k_ele":[{"e":"鎮台"}],"r_ele":[{"r":"ちんだい"}],"sense":[{"gloss":"garrison (in Meiji era)","pos":["n"]}]},{"k_ele":[{"e":"鎮守府"}],"r_ele":[{"r":"ちんじゅふ"}],"sense":[{"gloss":"naval district (of the Imperial Japanese Navy), naval station","pos":["n"]},{"gloss":"military base (for suppressing Emishi; in ancient Japan)","pos":["n"],"x":["蝦夷・1"]}],"m":["hist"]},{"k_ele":[{"e":"鎮魂祭"},{"e":"鎮魂の祭り"}],"r_ele":[{"r":"ちんこんさい"},{"r":"たましずめのまつり"}],"sense":[{"gloss":"ceremony for the repose of a soul","pos":["n"]},{"gloss":"ceremony to pray for the long life of the emperor, empress, crown prince, etc.","pos":["n"]}]},{"k_ele":[{"e":"鎮撫"}],"r_ele":[{"r":"ちんぶ"}],"sense":[{"gloss":"pacification, placating","pos":["n","vs","vt"]}]},{"k_ele":[{"e":"鎮護"}],"r_ele":[{"r":"ちんご"}],"sense":[{"gloss":"guarding, protecting","pos":["n","vs","vt"]}]},{"k_ele":[{"e":"取り鎮める"},{"e":"取鎮める"}],"r_ele":[{"r":"とりしずめる"}],"sense":[{"gloss":"to quell, to quiet","pos":["v1","vt"]}]},{"k_ele":[{"e":"風鎮"}],"r_ele":[{"r":"ふうちん"}],"sense":[{"gloss":"hanging-scroll weight","pos":["n"]}]},{"k_ele":[{"e":"鎮守の神"}],"r_ele":[{"r":"ちんじゅのかみ"}],"sense":[{"gloss":"local deity, guardian god","pos":["n"]}]},{"k_ele":[{"e":"鎮め物"}],"r_ele":[{"r":"しずめもの"}],"sense":[{"gloss":"sacred items buried in the ring during its ritual purification","pos":["n"],"f":["sumo"]}]},{"k_ele":[{"e":"鎮守社"}],"r_ele":[{"r":"ちんじゅしゃ"}],"sense":[{"gloss":"Shinto shrine on Buddhist temple grounds dedicated to the tutelary deity of the area","pos":["n"]}]},{"k_ele":[{"e":"郷鎮企業"}],"r_ele":[{"r":"ごうちんきぎょう"}],"sense":[{"gloss":"township and village enterprises (in China), TVE","pos":["n"]}]},{"k_ele":[{"e":"鎮祭"}],"r_ele":[{"r":"ちんさい"}],"sense":[{"gloss":"religious ceremony (to appease the gods)","pos":["n","vs"]}]},{"k_ele":[{"e":"鎮子"}],"r_ele":[{"r":"ちんし"},{"r":"ちんす"},{"r":"ちんじ"}],"sense":[{"gloss":"ornamental weights used to keep curtains and the like from blowing around in the wind","pos":["n"]}]},{"k_ele":[{"e":"鎮西派"}],"r_ele":[{"r":"ちんぜいは"}],"sense":[{"gloss":"Chinzei sect (of Pure Land Buddhism)","pos":["n"]}]},{"k_ele":[{"e":"鎮護国家"}],"r_ele":[{"r":"ちんごこっか"}],"sense":[{"gloss":"spiritual protection of the state","pos":["n"],"f":["Buddh"]}]},{"k_ele":[{"e":"鎮魂歌"}],"r_ele":[{"r":"ちんこんか"}],"sense":[{"gloss":"requiem","pos":["n"]}]},{"k_ele":[{"e":"麻薬性鎮痛薬"}],"r_ele":[{"r":"まやくせいちんつうやく"}],"sense":[{"gloss":"narcotic analgesic","pos":["n"]}]},{"k_ele":[{"e":"鎮静化"},{"e":"沈静化"}],"r_ele":[{"r":"ちんせいか"}],"sense":[{"gloss":"calming down, quieting down","pos":["n","vs"]}]},{"k_ele":[{"e":"鎮痙薬"}],"r_ele":[{"r":"ちんけいやく"}],"sense":[{"gloss":"antispasmodic drug, spasmolytic drug, anticonvulsant drug","pos":["n"]}]},{"k_ele":[{"e":"鎮痙剤"}],"r_ele":[{"r":"ちんけいざい"}],"sense":[{"gloss":"antispasmodic drug, spasmolytic drug, anticonvulsant drug","pos":["n"]}]},{"k_ele":[{"e":"鎮痙"}],"r_ele":[{"r":"ちんけい"}],"sense":[{"gloss":"spasmolysis","pos":["n"]},{"gloss":"spasmolytic, antispasmodic, anticonvulsive","pos":["adj-no"]}]},{"k_ele":[{"e":"鎮星"}],"r_ele":[{"r":"ちんせい"}],"sense":[{"gloss":"Saturn (planet)","pos":["n"],"x":["土星"]}]},{"k_ele":[{"e":"藩鎮"}],"r_ele":[{"r":"はんちん"}],"sense":[{"gloss":"jiedushi (regional military governor in ancient China)","pos":["n"],"x":["節度使"]}],"m":["hist"]},{"k_ele":[{"e":"暴動鎮圧"}],"r_ele":[{"r":"ぼうどうちんあつ"}],"sense":[{"gloss":"riot control","pos":["n"]}]}],"sdata":[{"j":"↑火事↑↓かじ↓は↑鎮火↑↓ちんか↓するまでかなりの↑間↑↓ま↓↑燃↑↓も↓え↑続↑↓つづ↓けていた。","e":"The fire went on for some time before it was brought under control."},{"j":"↑火事↑↓かじ↓は↑大事↑↓だいじ↓に↑至↑↓いた↓らず↑鎮火↑↓ちんか↓した。","e":"The fire was put out before it got serious."},{"j":"その↑暴動↑↓ぼうどう↓を↑鎮圧↑↓ちんあつ↓するには↑長↑↓なが↓い↑時間↑↓じかん↓がかかるだろう。","e":"It will take a long time to suppress the revolt."},{"j":"その↑暴動↑↓ぼうどう↓はすぐに↑警察↑↓けいさつ↓によって↑鎮圧↑↓ちんあつ↓された。","e":"The riot was soon put down by the police."},{"j":"その↑反乱↑↓はんらん↓を↑鎮圧↑↓ちんあつ↓するために↑軍隊↑↓ぐんたい↓の↑出動↑↓しゅつどう↓が↑要請↑↓ようせい↓された。","e":"The army was called to suppress the revolt."},{"j":"↑軍隊↑↓ぐんたい↓は↑暴動↑↓ぼうどう↓を↑簡単↑↓かんたん↓に↑鎮圧↑↓ちんあつ↓した。","e":"The troops easily put down the rebellion."},{"j":"↑軍隊↑↓ぐんたい↓は↑簡単↑↓かんたん↓に↑反乱↑↓はんらん↓を↑鎮圧↑↓ちんあつ↓した。","e":"The troops easily put down the rebellion."},{"j":"その↑軍隊↑↓ぐんたい↓は↑簡単↑↓かんたん↓に↑反乱↑↓はんらん↓を↑鎮圧↑↓ちんあつ↓した。","e":"The troops easily put down the rebellion."},{"j":"その↑火事↑↓かじ↓はすぐに↑鎮火↑↓ちんか↓された。","e":"The fire was soon extinguished."},{"j":"インフレは↑鎮静↑↓ちんせい↓↑化↑↓か↓しています。","e":"Inflation is down."},{"j":"↑軍隊↑↓ぐんたい↓はまもなく↑反乱↑↓はんらん↓を↑鎮↑↓しず↓めた。","e":"The troops soon put down the rebellion."},{"j":"↑警察↑↓けいさつ↓は↑暴走↑↓ぼうそう↓↑族↑↓ぞく↓を↑躍起↑↓やっき↓になって↑鎮圧↑↓ちんあつ↓しようとしている。","e":"The police are going all out to keep down the rioting bikers."},{"j":"↑混乱↑↓こんらん↓はすっかり↑鎮↑↓しず↓まった。","e":"The confusion is all over."},{"j":"↑頭↑↓あたま↓が↑痛↑↓いた↓いときは↑鎮痛↑↓ちんつう↓↑剤↑↓ざい↓を↑飲↑↓の↓まずにはいられない。","e":"I can't help taking painkillers when I have a headache."},{"j":"↑私↑↓わたし↓は↑頭↑↓あたま↓が↑痛↑↓いた↓くなると↑鎮痛↑↓ちんつう↓↑剤↑↓ざい↓を↑飲↑↓の↓まずにいられない。","e":"I can't help taking painkillers when I have a headache."},{"j":"↑政府↑↓せいふ↓↑当局↑↓とうきょく↓は↑暴動↑↓ぼうどう↓を↑鎮圧↑↓ちんあつ↓するために↑軍↑↓ぐん↓を↑出動↑↓しゅつどう↓させました。","e":"The authorities sent in troops to quell the riot."},{"j":"↑鎮痛↑↓ちんつう↓↑剤↑↓ざい↓はありますか。","e":"Do you have a pain reliever?"},{"j":"↑鎮痛↑↓ちんつう↓↑剤↑↓ざい↓は↑痛↑↓いた↓いときだけ↑飲↑↓の↓んでください。","e":"Take the pain reliever only when you need it."},{"j":"↑痛↑↓いた↓くなったら↑鎮痛↑↓ちんつう↓↑剤↑↓ざい↓を↑飲↑↓の↓んでください。","e":"If you have pain, take a painkiller."},{"j":"↑反乱↑↓はんらん↓は↑鎮圧↑↓ちんあつ↓された。","e":"The revolt was crushed."},{"j":"↑彼↑↓かれ↓はインドの↑反乱↑↓はんらん↓を↑鎮↑↓しず↓めた。","e":"He put down the rebellion in India."},{"j":"↑彼↑↓かれ↓らは↑鎮火↑↓ちんか↓するために↑互↑↓たが↓いに↑協力↑↓きょうりょく↓した。","e":"They worked together to put out the fire."},{"j":"↑彼女↑↓かのじょ↓は↑話↑↓はな↓す↑前↑↓まえ↓に↑気↑↓き↓を↑鎮↑↓しず↓めた。","e":"She composed herself before speaking."},{"j":"↑暴動↑↓ぼうどう↓はすぐに↑鎮↑↓しず↓められた。","e":"The rebellion was soon put down."},{"j":"↑暴動↑↓ぼうどう↓を↑鎮圧↑↓ちんあつ↓するためにただちに↑軍隊↑↓ぐんたい↓が↑派遣↑↓はけん↓された。","e":"Troops were swiftly called in to put down the riot."},{"j":"これまでアメリカは↑世界↑↓せかい↓の↑警察↑↓けいさつ↓と↑称↑↓しょう↓して↑武力↑↓ぶりょく↓に↑頼↑↓たよ↓った↑鎮圧↑↓ちんあつ↓を↑続↑↓つづ↓けてきました。","e":"Up till now America has called itself the world's police and continued suppression relying on military force."},{"j":"↑波風↑↓なみかぜ↓を↑鎮↑↓しず↓めるにはチーズケーキのお↑土産↑↓みやげ↓が↑良↑↓よ↓いらしいですよ。","e":"A gift of cheesecake is apparently good to soothe discord."},{"j":"↑医者↑↓いしゃ↓に↑相談↑↓そうだん↓して↑鎮静↑↓ちんせい↓↑剤↑↓ざい↓を↑処方↑↓しょほう↓してもらうのはどうでしょうか。","e":"How about consulting a doctor and getting sedatives prescribed?"},{"j":"よって↑流通↑↓りゅうつう↓するマネーが↑減↑↓へ↓り、↑物価↑↓ぶっか↓↑上昇↑↓じょうしょう↓は↑鎮静↑↓ちんせい↓↑化↑↓か↓する。","e":"Thus money in circulation drops, and price escalation quietens down."},{"j":"↑鎮痛↑↓ちんつう↓↑剤↑↓ざい↓を↑飲↑↓の↓みなさい。","e":"Take some aspirin."}],"kdata":{"on":["チン"],"kun":["しず.める","しず.まる","おさえ"],"jlpt":1,"meanings":["tranquilize","ancient peace-preservation centers"],"freq":1617,"comp":[["真","金"]],"t":2245},"c":{"meanings":["tranquilize","ancient peace-preservation centers"],"on":["チン"],"kun":["しず.める","しず.まる","おさえ"]}}