{"jdata":[{"k_ele":[{"e":"虫歯","p":true},{"e":"むし歯"},{"e":"齲歯"},{"e":"齲"}],"r_ele":[{"r":"むしば","p":true},{"r":"うし"},{"r":"くし"}],"sense":[{"gloss":"cavity, tooth decay, decayed tooth, dental caries","pos":["n"]}]},{"k_ele":[{"e":"う蝕"},{"e":"齲蝕"},{"e":"う食","i":["iK"]},{"e":"齲食","i":["iK"]}],"r_ele":[{"r":"うしょく"}],"sense":[{"gloss":"dental caries, tooth decay","pos":["n"],"f":["med"]}]}],"kdata":{"on":["ク","ウ"],"kun":["むしば"],"meanings":["decayed tooth","cavity"],"comp":[["禹","齒"]],"freq":4383},"c":{"meanings":["decayed tooth","cavity"],"on":["ク","ウ"],"kun":["むしば"]}}